[
    {
        "filename": "default", 
        "description": "Default"
    },
    {
        "filename": "guangzhou_gz1", 
        "description": "Guangzhou Metro - Line 1"
    }, 
    {
        "filename": "guangzhou_gz3", 
        "description": "Guangzhou Metro - Line 3"
    }, 
    {
        "filename": "guangzhou_gz8", 
        "description": "Guangzhou Metro - Line 8"
    }, 
    {
        "filename": "guangzhou_gz14", 
        "description": "Guangzhou Metro - Line 14"
    }, 
    {
        "filename": "guangzhou_gz21", 
        "description": "Guangzhou Metro - Line 21"
    }, 
    {
        "filename": "macau_taipa", 
        "description": "Metro Ligeiro de Macau - Linha Taipa"
    },
    {
        "filename": "hongkong_eal", 
        "description": "MTR - East Rail Line"
    },
    {
        "filename": "hongkong_tkl", 
        "description": "MTR - Tseung Kwan O Line"
    },
    {
        "filename": "hongkong_twl", 
        "description": "MTR - Tsuen Wan Line"
    },
    {
        "filename": "prdir_guangzhu", 
        "description": "PRDIR - Guangzhou-Zhuhai Intercity"
    }
]